{
  "previous": {
    "date": "2026-07-08",
    "order": [
      "Shah Qureshi",
      "Darren Cooney",
      "Simon Champion-MacPherson",
      "Sean Blakeley",
      "Adam Hollister",
      "Ryan Golds",
      "Chris McConney",
      "Carmine Colicino",
      "Dimitra Chaloglou",
      "Georgia Cottle",
      "John Jeeves",
      "Tom Reed"
    ]
  },
  "current": {
    "date": "2026-07-09",
    "order": [
      "Shah Qureshi",
      "Darren Cooney",
      "Simon Champion-MacPherson",
      "Sean Blakeley",
      "Adam Hollister",
      "Ryan Golds",
      "Chris McConney",
      "Carmine Colicino",
      "Dimitra Chaloglou",
      "Georgia Cottle",
      "John Jeeves",
      "Tom Reed"
    ]
  }
}
